organizador_planilha/__init__.py
organizador_planilha/db_utils.py
organizador_planilha/gui.py
organizador_planilha/organizador.py
organizador_planilha-1.dist-info/LICENSE
organizador_planilha-1.dist-info/METADATA
organizador_planilha-1.dist-info/WHEEL
organizador_planilha-1.dist-info/top_level.txt
organizador_planilha-1.dist-info/RECORD
