Metadata-Version: 2.1
Name: organizador_planilha
Version: 1
Summary: Um pacote simples para buscar e organizar planilhas em um banco MYSQL
Home-page: https://github.com/MoisesAlves2023/organizador_planilha
Author: Moisés Alves
Author-email: moisesalvespc@gmail.com
Classifier: Programming Language :: Python :: 3
Classifier: License :: OSI Approved :: MIT License
Classifier: Operating System :: OS Independent
Requires-Python: >=3.6
License-File: LICENSE
Requires-Dist: pandas
Requires-Dist: sqlalchemy
Requires-Dist: openpyxl
Requires-Dist: pymysql
